scrawl/__init__.py
scrawl/cli.py
scrawl/commands/__init__.py
scrawl/commands/cmd_createnote.py
scrawl/commands/cmd_deletenote.py
scrawl/commands/cmd_export.py
scrawl/commands/cmd_import.py
scrawl/commands/cmd_init.py
scrawl/commands/cmd_listnotes.py
scrawl/commands/cmd_searchnotes.py
scrawl/commands/cmd_status.py
scrawl/commands/cmd_sync.py
scrawl/commands/cmd_viewnote.py
scrawl/commands2/__init__.py
scrawl/commands2/cmd_createnote.py
scrawl/commands2/cmd_deletenote.py
scrawl/commands2/cmd_export.py
scrawl/commands2/cmd_import.py
scrawl/commands2/cmd_init.py
scrawl/commands2/cmd_listnotes.py
scrawl/commands2/cmd_searchnotes.py
scrawl/commands2/cmd_status.py
scrawl/commands2/cmd_sync.py
scrawl/commands2/cmd_viewnote.py
scrawl/helpers/__init__.py
scrawl/helpers/db.py
scrawl/helpers/hash.py
scrawl/helpers/helpers.py
scrawl-1.0.6.dist-info/DESCRIPTION.rst
scrawl-1.0.6.dist-info/METADATA
scrawl-1.0.6.dist-info/RECORD
scrawl-1.0.6.dist-info/WHEEL
scrawl-1.0.6.dist-info/entry_points.txt
scrawl-1.0.6.dist-info/metadata.json
scrawl-1.0.6.dist-info/top_level.txt
