Metadata-Version: 2.0
Name: scrawl
Version: 1.0.6
Summary: A python note-taking console app 
Home-page: https://github.com/ten-c/bc-6-scrawl
Author: Ten Chege
Author-email: 10.chege@gmail.com
License: UNKNOWN
Keywords: sample setuptools development
Platform: UNKNOWN
Requires-Dist: Click
Requires-Dist: colorama
Requires-Dist: python-firebase
